{"type":"Sprite","props":{"y":0,"x":0,"scaleY":1,"presetID":1,"name":"BgNode","isPresetRoot":true},"compId":4,"child":[{"type":"Image","props":{"y":-640,"x":360,"skin":"lobby/bg_zhujiemian_putong.png","scaleY":-1,"presetID":3,"anchorY":0.5,"anchorX":0.5},"compId":9},{"type":"Image","props":{"y":640,"x":360,"skin":"lobby/bg_zhujiemian_putong.png","presetID":2,"anchorY":0.5,"anchorX":0.5},"compId":8},{"type":"Script","props":{"presetID":4,"bg2":"@node:8","bg1":"@node:9","runtime":"battle/BgNode.ts"},"compId":10}],"loadList":["lobby/bg_zhujiemian_putong.png"],"loadList3D":[]}